Metadata-Version: 2.1
Name: GenerNation
Version: 0.0.8
Summary: Tool for generating various characters
Home-page: https://github.com/artegoser/GenerNation
Author: artegoser
Author-email: artegoser@gmail.com
License: MIT
Platform: UNKNOWN
